uv_bump/__init__.py
uv_bump/cli.py
uv_bump/main.py
uv_bump-0.4.2.dist-info/licenses/LICENSE
uv_bump-0.4.2.dist-info/WHEEL
uv_bump-0.4.2.dist-info/entry_points.txt
uv_bump-0.4.2.dist-info/METADATA
uv_bump-0.4.2.dist-info/RECORD
