Metadata-Version: 2.4
Name: uv-bump
Version: 0.4.2
Summary: Bump pyproject.toml dependency minimum versions to latest feasible versions.
Keywords: uv,bump,version,dependency,upgrade,pyproject.toml,cli
Author: Jeroen van Zundert
Author-email: Jeroen van Zundert <mail@jeroenvanzundert.nl>
License-Expression: MIT
License-File: LICENSE
Classifier: Development Status :: 4 - Beta
Classifier: Intended Audience :: Developers
Classifier: Topic :: Software Development :: Build Tools
Classifier: Programming Language :: Python :: 3.10
Classifier: Programming Language :: Python :: 3.11
Classifier: Programming Language :: Python :: 3.12
Classifier: Programming Language :: Python :: 3.13
Classifier: Programming Language :: Python :: 3.14
Requires-Dist: tomli>=2.3.0 ; python_full_version < '3.11'
Requires-Python: >=3.10
Project-URL: Homepage, https://github.com/zundertj/uv-bump
Project-URL: Issues, https://github.com/zundertj/uv-bump/issues
Project-URL: Repository, https://github.com/zundertj/uv-bump.git
